logilab/mtconverter/__init__.py
logilab/mtconverter/engine.py
logilab/mtconverter/py.typed
logilab/mtconverter/transform.py
logilab/mtconverter/transforms/__init__.py
logilab/mtconverter/transforms/cmdtransforms.py
logilab/mtconverter/transforms/htmltransform.py
logilab/mtconverter/transforms/odt2text.py
logilab/mtconverter/transforms/pgpsignature.py
logilab/mtconverter/transforms/piltransforms.py
logilab/mtconverter/transforms/pygmentstransforms.py
logilab/mtconverter/transforms/python.py
logilab_mtconverter-1.0.dist-info/COPYING
logilab_mtconverter-1.0.dist-info/COPYING.LESSER
logilab_mtconverter-1.0.dist-info/METADATA
logilab_mtconverter-1.0.dist-info/WHEEL
logilab_mtconverter-1.0.dist-info/top_level.txt
logilab_mtconverter-1.0.dist-info/RECORD
