Metadata-Version: 2.1
Name: logilab-mtconverter
Version: 1.0
Summary: a library to convert from a MIME type to another
Home-page: https://www.logilab.org/project/logilab-mtconverter
Author: Nicolas Chauvat
Author-email: contact@logilab.fr
License: LGPL
Classifier: Programming Language :: Python
Classifier: Programming Language :: Python :: 3
Classifier: Programming Language :: Python :: 3 :: Only
Requires-Python: >=3.6
License-File: COPYING
License-File: COPYING.LESSER
Requires-Dist: setuptools
Requires-Dist: logilab-common <3.0.0,>=2.0.0
Requires-Dist: lxml
Requires-Dist: html2text
Requires-Dist: importlib-metadata ; python_version < "3.10"
